bbc_pkg/__init__.py
bbc_pkg_BBC-0.0.1.dist-info/LICENSE
bbc_pkg_BBC-0.0.1.dist-info/METADATA
bbc_pkg_BBC-0.0.1.dist-info/WHEEL
bbc_pkg_BBC-0.0.1.dist-info/top_level.txt
bbc_pkg_BBC-0.0.1.dist-info/RECORD
